easysweeps/__init__.py
easysweeps/cli.py
easysweeps/config.py
easysweeps/constants.py
easysweeps/launch_agents.py
easysweeps/launch_sweeps.py
easysweeps/utils.py
easysweeps-0.4.6.dist-info/licenses/LICENSE
easysweeps-0.4.6.dist-info/METADATA
easysweeps-0.4.6.dist-info/WHEEL
easysweeps-0.4.6.dist-info/entry_points.txt
easysweeps-0.4.6.dist-info/top_level.txt
easysweeps-0.4.6.dist-info/RECORD
